{
	"language": [
		{
			"title":   "Hello World!",
			"welcome": "This site is a mess and, probably, it will to look like this for a \"\"\"little time\"\"\" <s>(really i'm lousy with sites)</s>.",
			"about":   "In below you can find some <i>links</i><br>related my work:",
		}, {
			"title":   "Olá mundo!",
			"welcome": "Esse site está uma bagunça e, provavelmente, vai ficar assim por um \"\"\"tempinho\"\"\" <s>(realmente sou péssimo com sites)</s>.",
			"about":   "Abaixo você poderá encontrar alguns <i>links</i><br>relacionados ao meu trabalho:",
		},
	]
}